LICENSE
README.md
setup.cfg
setup.py
asyncio_context/__init__.py
asyncio_context/context.py
asyncio_context/logging.py
asyncio_context.egg-info/PKG-INFO
asyncio_context.egg-info/SOURCES.txt
asyncio_context.egg-info/dependency_links.txt
asyncio_context.egg-info/top_level.txt
examples/__init__.py