Metadata-Version: 2.1
Name: asyncio-context
Version: 0.0.1
Summary: Asyncio task context with logging support
Home-page: https://github.com/Serhg94/asyncio-context
Author: Sergey Lobarev
Author-email: serhg94@gmail.com
License: MIT
Keywords: asyncio,aiohttp,context,trace,annotations
Platform: UNKNOWN
Classifier: Intended Audience :: Developers
Classifier: Intended Audience :: Information Technology
Classifier: Programming Language :: Python
Classifier: Programming Language :: Python :: 3
Classifier: Programming Language :: Python :: 3 :: Only
Classifier: Programming Language :: Python :: 3.8
Classifier: Programming Language :: Python :: 3.9
Classifier: Topic :: Software Development :: Libraries
Classifier: License :: OSI Approved :: MIT License
Requires-Python: >=3.8
License-File: LICENSE
